napari_result_stack/__init__.py
napari_result_stack/_models.py
napari_result_stack/_qt_const.py
napari_result_stack/_register_types.py
napari_result_stack/napari.yaml
napari_result_stack/testing.py
napari_result_stack/types.py
napari_result_stack/_tests/__init__.py
napari_result_stack/_tests/conftest.py
napari_result_stack/_tests/test_factory.py
napari_result_stack/_tests/test_stored_type_basic.py
napari_result_stack/_tests/test_widget.py
napari_result_stack/factory/__init__.py
napari_result_stack/factory/_dict_view.py
napari_result_stack/factory/_factory.py
napari_result_stack/factory/_factory_default.py
napari_result_stack/factory/_table_view.py
napari_result_stack/factory/_text_view.py
napari_result_stack/widgets/__init__.py
napari_result_stack/widgets/_main.py
napari_result_stack/widgets/_result_stack.py
napari_result_stack-0.0.1.dist-info/LICENSE
napari_result_stack-0.0.1.dist-info/METADATA
napari_result_stack-0.0.1.dist-info/WHEEL
napari_result_stack-0.0.1.dist-info/entry_points.txt
napari_result_stack-0.0.1.dist-info/top_level.txt
napari_result_stack-0.0.1.dist-info/RECORD
